LICENSE
MANIFEST.in
README.md
pyproject.toml
setup.py
examples/__init__.py
examples/walking.py
ksim/__init__.py
ksim/actions.py
ksim/actuators.py
ksim/commands.py
ksim/curriculum.py
ksim/dataset.py
ksim/debugging.py
ksim/engine.py
ksim/events.py
ksim/noise.py
ksim/observation.py
ksim/py.typed
ksim/randomization.py
ksim/requirements-dev.txt
ksim/requirements.txt
ksim/resets.py
ksim/rewards.py
ksim/terminations.py
ksim/types.py
ksim/vis.py
ksim.egg-info/PKG-INFO
ksim.egg-info/SOURCES.txt
ksim.egg-info/dependency_links.txt
ksim.egg-info/entry_points.txt
ksim.egg-info/requires.txt
ksim.egg-info/top_level.txt
ksim/task/__init__.py
ksim/task/amp.py
ksim/task/ppo.py
ksim/task/rl.py
ksim/task/teacher.py
ksim/utils/__init__.py
ksim/utils/api.py
ksim/utils/mujoco.py
ksim/utils/priors.py
ksim/utils/validators.py
tests/test_commands.py
tests/test_observation.py
tests/test_randomizations.py
tests/test_resets.py
tests/test_rewards.py
tests/test_terminations.py
tests/test_training_e2e.py