Metadata-Version: 2.4
Name: ksim
Version: 0.2.9
Summary: A modular and easy-to-use framework for training policies in simulation.
Home-page: https://github.com/kscalelabs/ksim
Author: K-Scale Labs
Requires-Python: >=3.11
License-File: LICENSE
Requires-Dist: numpy
Requires-Dist: matplotlib
Requires-Dist: tqdm
Requires-Dist: tabulate
Requires-Dist: kscale
Requires-Dist: jax
Requires-Dist: mediapy
Requires-Dist: optax
Requires-Dist: scipy
Requires-Dist: xax
Requires-Dist: mujoco
Requires-Dist: mujoco-mjx
Requires-Dist: kmv
Requires-Dist: bvhio
Requires-Dist: pyglm
Provides-Extra: dev
Requires-Dist: mypy; extra == "dev"
Requires-Dist: pytest; extra == "dev"
Requires-Dist: ruff; extra == "dev"
Dynamic: author
Dynamic: description
Dynamic: description-content-type
Dynamic: home-page
Dynamic: license-file
Dynamic: provides-extra
Dynamic: requires-dist
Dynamic: requires-python
Dynamic: summary
